utsav/__init__.py
utsav/main.py
utsav-0.2.5.dist-info/METADATA
utsav-0.2.5.dist-info/WHEEL
utsav-0.2.5.dist-info/top_level.txt
utsav-0.2.5.dist-info/RECORD
