Metadata-Version: 2.1
Name: utsav
Version: 0.2.5
Summary: Created to work with big microbiome data
Home-page: https://www.utsavlamichhane.com
Author: Utsav Lamichhane
Author-email: utsav.lamichhane@gmail.com
Requires-Dist: pandas
Requires-Dist: matplotlib
Requires-Dist: scikit-learn
